{"country":"SV","name":"El Salvador","name_zh":"萨尔瓦多","admin1s":{"05":{"name":"05","name_local":"05","cities":[{"id":"3584257","n":"Santa Tecla","a":"Santa Tecla","lat":13.6774,"lng":-89.2833,"tz":"America/El_Salvador","p":124694},{"id":"3587362","n":"Antiguo Cuscatlán","a":"Antiguo Cuscatlan","lat":13.6649,"lng":-89.2532,"tz":"America/El_Salvador","p":33767},{"id":"3583981","n":"Quezaltepeque","a":"Quezaltepeque","lat":13.8312,"lng":-89.2722,"tz":"America/El_Salvador","p":28886},{"id":"3585157","n":"La Libertad","a":"La Libertad","lat":13.4883,"lng":-89.3222,"tz":"America/El_Salvador","p":16855},{"id":"3582790","n":"Zaragoza","a":"Zaragoza","lat":13.5894,"lng":-89.2889,"tz":"America/El_Salvador","p":11749},{"id":"3586985","n":"Ciudad Arce","a":"Ciudad Arce","lat":13.8403,"lng":-89.4472,"tz":"America/El_Salvador","p":10095},{"id":"3583531","n":"San Juan Opico","a":"San Juan Opico","lat":13.8761,"lng":-89.3597,"tz":"America/El_Salvador","p":7127},{"id":"3584251","n":"Nuevo Cuscatlán","a":"Nuevo Cuscatlan","lat":13.6486,"lng":-89.2653,"tz":"America/El_Salvador","p":6469},{"id":"3583429","n":"San Pablo Tacachico","a":"San Pablo Tacachico","lat":13.9756,"lng":-89.34,"tz":"America/El_Salvador","p":3033}]},"06":{"name":"06","name_local":"06","cities":[{"id":"3582805","n":"Zacatecoluca","a":"Zacatecoluca","lat":13.5087,"lng":-88.8702,"tz":"America/El_Salvador","p":39613},{"id":"3583196","n":"Santiago Nonualco","a":"Santiago Nonualco","lat":13.5167,"lng":-88.95,"tz":"America/El_Salvador","p":9490},{"id":"3584212","n":"Olocuilta","a":"Olocuilta","lat":13.5697,"lng":-89.1172,"tz":"America/El_Salvador","p":6324},{"id":"3586021","n":"El Rosario","a":"El Rosario","lat":13.4978,"lng":-89.0297,"tz":"America/El_Salvador","p":5620},{"id":"3583407","n":"San Pedro Masahuat","a":"San Pedro Masahuat","lat":13.5436,"lng":-89.0386,"tz":"America/El_Salvador","p":2654}]},"02":{"name":"02","name_local":"02","cities":[{"id":"3583158","n":"Sensuntepeque","a":"Sensuntepeque","lat":13.8758,"lng":-88.6273,"tz":"America/El_Salvador","p":20386},{"id":"3582835","n":"Victoria","a":"Victoria","lat":13.95,"lng":-88.6333,"tz":"America/El_Salvador","p":2023}]},"14":{"name":"14","name_local":"14","cities":[{"id":"3582883","n":"Usulután","a":"Usulutan","lat":13.3447,"lng":-88.4399,"tz":"America/El_Salvador","p":51910},{"id":"3584003","n":"Puerto El Triunfo","a":"Puerto El Triunfo","lat":13.2833,"lng":-88.55,"tz":"America/El_Salvador","p":19074},{"id":"3583199","n":"Santiago de María","a":"Santiago de Maria","lat":13.4833,"lng":-88.4667,"tz":"America/El_Salvador","p":15032},{"id":"3587266","n":"Berlín","a":"Berlin","lat":13.5,"lng":-88.5333,"tz":"America/El_Salvador","p":11313},{"id":"3585398","n":"Jucuapa","a":"Jucuapa","lat":13.5167,"lng":-88.3833,"tz":"America/El_Salvador","p":10601},{"id":"3585438","n":"Jiquilisco","a":"Jiquilisco","lat":13.3167,"lng":-88.5833,"tz":"America/El_Salvador","p":9129},{"id":"3583278","n":"Santa Elena","a":"Santa Elena","lat":13.3833,"lng":-88.4167,"tz":"America/El_Salvador","p":5887},{"id":"3584190","n":"Ozatlán","a":"Ozatlan","lat":13.3833,"lng":-88.5,"tz":"America/El_Salvador","p":4171},{"id":"3586930","n":"Concepción Batres","a":"Concepcion Batres","lat":13.35,"lng":-88.3667,"tz":"America/El_Salvador","p":3286},{"id":"3583910","n":"San Agustín","a":"San Agustin","lat":13.4333,"lng":-88.6,"tz":"America/El_Salvador","p":2149},{"id":"3585395","n":"Jucuarán","a":"Jucuaran","lat":13.2539,"lng":-88.2478,"tz":"America/El_Salvador","p":1643}]},"01":{"name":"01","name_local":"01","cities":[{"id":"3587426","n":"Ahuachapán","a":"Ahuachapan","lat":13.924,"lng":-89.8434,"tz":"America/El_Salvador","p":34102},{"id":"3582896","n":"Turín","a":"Turin","lat":13.9664,"lng":-89.7661,"tz":"America/El_Salvador","p":11829},{"id":"3587317","n":"Atiquizaya","a":"Atiquizaya","lat":13.9769,"lng":-89.7525,"tz":"America/El_Salvador","p":9476},{"id":"3586926","n":"Concepción de Ataco","a":"Concepcion de Ataco","lat":13.8703,"lng":-89.8486,"tz":"America/El_Salvador","p":7797},{"id":"3583065","n":"Tacuba","a":"Tacuba","lat":13.9011,"lng":-89.9297,"tz":"America/El_Salvador","p":5055},{"id":"3585392","n":"Jujutla","a":"Jujutla","lat":13.7869,"lng":-89.8572,"tz":"America/El_Salvador","p":2022},{"id":"3585640","n":"Guaymango","a":"Guaymango","lat":13.7503,"lng":-89.8422,"tz":"America/El_Salvador","p":1517},{"id":"3583716","n":"San Francisco Menéndez","a":"San Francisco Menendez","lat":13.8431,"lng":-90.0158,"tz":"America/El_Salvador","p":1264}]},"10":{"name":"10","name_local":"10","cities":[{"id":"3583361","n":"San Salvador","a":"San Salvador","lat":13.6893,"lng":-89.1872,"tz":"America/El_Salvador","p":525990},{"id":"3583096","n":"Soyapango","a":"Soyapango","lat":13.7102,"lng":-89.1399,"tz":"America/El_Salvador","p":329708},{"id":"3584399","n":"Mejicanos","a":"Mejicanos","lat":13.724,"lng":-89.188,"tz":"America/El_Salvador","p":160317},{"id":"3587345","n":"Apopa","a":"Apopa","lat":13.8072,"lng":-89.1792,"tz":"America/El_Salvador","p":112158},{"id":"3586814","n":"Delgado","a":"Delgado","lat":13.7217,"lng":-89.1687,"tz":"America/El_Salvador","p":71594},{"id":"3583480","n":"San Marcos","a":"San Marcos","lat":13.6611,"lng":-89.1825,"tz":"America/El_Salvador","p":54615},{"id":"3586833","n":"Cuscatancingo","a":"Cuscatancingo","lat":13.727,"lng":-89.1816,"tz":"America/El_Salvador","p":44369},{"id":"3585484","n":"Ilopango","a":"Ilopango","lat":13.7017,"lng":-89.1094,"tz":"America/El_Salvador","p":38890},{"id":"3587308","n":"Ayutuxtepeque","a":"Ayutuxtepeque","lat":13.7354,"lng":-89.2022,"tz":"America/El_Salvador","p":25426},{"id":"3587428","n":"Aguilares","a":"Aguilares","lat":13.9572,"lng":-89.1897,"tz":"America/El_Salvador","p":21445},{"id":"3583183","n":"Santo Tomás","a":"Santo Tomas","lat":13.6408,"lng":-89.1333,"tz":"America/El_Salvador","p":14581},{"id":"3585636","n":"Guazapa","a":"Guazapa","lat":13.8769,"lng":-89.1731,"tz":"America/El_Salvador","p":10995},{"id":"3584156","n":"Panchimalco","a":"Panchimalco","lat":13.6128,"lng":-89.18,"tz":"America/El_Salvador","p":6764},{"id":"3582918","n":"Tonacatepeque","a":"Tonacatepeque","lat":13.7811,"lng":-89.1186,"tz":"America/El_Salvador","p":6245},{"id":"3583937","n":"Rosario de Mora","a":"Rosario de Mora","lat":13.5753,"lng":-89.2089,"tz":"America/El_Salvador","p":5178},{"id":"3586204","n":"El Paisnal","a":"El Paisnal","lat":13.9736,"lng":-89.2186,"tz":"America/El_Salvador","p":1641}]},"11":{"name":"11","name_local":"11","cities":[{"id":"3583334","n":"Santa Ana","a":"Santa Ana","lat":13.9883,"lng":-89.5568,"tz":"America/El_Salvador","p":176661},{"id":"3587086","n":"Chalchuapa","a":"Chalchuapa","lat":13.9867,"lng":-89.6811,"tz":"America/El_Salvador","p":32282},{"id":"3584384","n":"Metapán","a":"Metapan","lat":14.3333,"lng":-89.45,"tz":"America/El_Salvador","p":19143},{"id":"3586550","n":"El Congo","a":"El Congo","lat":13.9089,"lng":-89.4958,"tz":"America/El_Salvador","p":8905},{"id":"3587157","n":"Candelaria de La Frontera","a":"Candelaria de La Frontera","lat":14.1167,"lng":-89.65,"tz":"America/El_Salvador","p":6301},{"id":"3586981","n":"Coatepeque","a":"Coatepeque","lat":13.9286,"lng":-89.5042,"tz":"America/El_Salvador","p":5773},{"id":"3582954","n":"Texistepeque","a":"Texistepeque","lat":14.1333,"lng":-89.5,"tz":"America/El_Salvador","p":2401}]},"04":{"name":"04","name_local":"04","cities":[{"id":"3586977","n":"Cojutepeque","a":"Cojutepeque","lat":13.7197,"lng":-88.9331,"tz":"America/El_Salvador","p":48411},{"id":"3583471","n":"San Martín","a":"San Martin","lat":13.7833,"lng":-88.9167,"tz":"America/El_Salvador","p":39361},{"id":"3583090","n":"Suchitoto","a":"Suchitoto","lat":13.9381,"lng":-89.0278,"tz":"America/El_Salvador","p":5735},{"id":"3583009","n":"Tecoluca","a":"Tecoluca","lat":13.7892,"lng":-89.0053,"tz":"America/El_Salvador","p":2781},{"id":"3582987","n":"Tenancingo","a":"Tenancingo","lat":13.8333,"lng":-88.9833,"tz":"America/El_Salvador","p":1011}]},"13":{"name":"13","name_local":"13","cities":[{"id":"3583102","n":"Sonsonate","a":"Sonsonate","lat":13.7173,"lng":-89.723,"tz":"America/El_Salvador","p":59468},{"id":"3587498","n":"Acajutla","a":"Acajutla","lat":13.5928,"lng":-89.8275,"tz":"America/El_Salvador","p":22763},{"id":"3585473","n":"Izalco","a":"Izalco","lat":13.7447,"lng":-89.6731,"tz":"America/El_Salvador","p":19197},{"id":"3583098","n":"Sonzacate","a":"Sonzacate","lat":13.7342,"lng":-89.7147,"tz":"America/El_Salvador","p":15446},{"id":"3587333","n":"Armenia","a":"Armenia","lat":13.7436,"lng":-89.4989,"tz":"America/El_Salvador","p":14997},{"id":"3585401","n":"Juayúa","a":"Juayua","lat":13.8414,"lng":-89.7456,"tz":"America/El_Salvador","p":9936},{"id":"3583851","n":"San Antonio del Monte","a":"San Antonio del Monte","lat":13.7164,"lng":-89.7383,"tz":"America/El_Salvador","p":9135},{"id":"3584297","n":"Nahuizalco","a":"Nahuizalco","lat":13.7775,"lng":-89.7367,"tz":"America/El_Salvador","p":7358}]},"08":{"name":"08","name_local":"08","cities":[{"id":"3583747","n":"San Francisco","a":"San Francisco","lat":13.6941,"lng":-88.1041,"tz":"America/El_Salvador","p":16152},{"id":"3585653","n":"Guatajiagua","a":"Guatajiagua","lat":13.6667,"lng":-88.2,"tz":"America/El_Salvador","p":5273},{"id":"3585427","n":"Jocoro","a":"Jocoro","lat":13.6167,"lng":-88.0167,"tz":"America/El_Salvador","p":4298},{"id":"3586884","n":"Corinto","a":"Corinto","lat":13.8108,"lng":-87.9714,"tz":"America/El_Salvador","p":3160},{"id":"3587208","n":"Cacaopera","a":"Cacaopera","lat":13.7667,"lng":-88.0833,"tz":"America/El_Salvador","p":2528},{"id":"3583111","n":"Sociedad","a":"Sociedad","lat":13.7,"lng":-88.0167,"tz":"America/El_Salvador","p":1770}]},"09":{"name":"09","name_local":"09","cities":[{"id":"3583446","n":"San Miguel","a":"San Miguel","lat":13.4826,"lng":-88.1821,"tz":"America/El_Salvador","p":247126},{"id":"3583379","n":"San Rafael Oriente","a":"San Rafael Oriente","lat":13.3833,"lng":-88.35,"tz":"America/El_Salvador","p":19095},{"id":"3585856","n":"El Tránsito","a":"El Transito","lat":13.35,"lng":-88.35,"tz":"America/El_Salvador","p":9485},{"id":"3587037","n":"Chinameca","a":"Chinameca","lat":13.5,"lng":-88.35,"tz":"America/El_Salvador","p":8646},{"id":"3586983","n":"Ciudad Barrios","a":"Ciudad Barrios","lat":13.7667,"lng":-88.2667,"tz":"America/El_Salvador","p":8491},{"id":"3587018","n":"Chirilagua","a":"Chirilagua","lat":13.2203,"lng":-88.1386,"tz":"America/El_Salvador","p":6393},{"id":"3584260","n":"Nueva Guadalupe","a":"Nueva Guadalupe","lat":13.5333,"lng":-88.35,"tz":"America/El_Salvador","p":5798},{"id":"3587064","n":"Chapeltique","a":"Chapeltique","lat":13.6333,"lng":-88.2667,"tz":"America/El_Salvador","p":3159},{"id":"3584714","n":"Lolotique","a":"Lolotique","lat":13.55,"lng":-88.35,"tz":"America/El_Salvador","p":2654},{"id":"3584348","n":"Moncagua","a":"Moncagua","lat":13.5333,"lng":-88.25,"tz":"America/El_Salvador","p":2148},{"id":"3583155","n":"Sesori","a":"Sesori","lat":13.7167,"lng":-88.3667,"tz":"America/El_Salvador","p":1390}]},"12":{"name":"12","name_local":"12","cities":[{"id":"3583178","n":"San Vicente","a":"San Vicente","lat":13.6411,"lng":-88.7846,"tz":"America/El_Salvador","p":41504},{"id":"3583352","n":"San Sebastián","a":"San Sebastian","lat":13.7333,"lng":-88.8333,"tz":"America/El_Salvador","p":7333},{"id":"3587349","n":"Apastepeque","a":"Apastepeque","lat":13.6667,"lng":-88.7833,"tz":"America/El_Salvador","p":5785}]},"07":{"name":"07","name_local":"07","cities":[{"id":"3584772","n":"La Unión","a":"La Union","lat":13.3392,"lng":-87.8433,"tz":"America/El_Salvador","p":26807},{"id":"3583214","n":"Santa Rosa de Lima","a":"Santa Rosa de Lima","lat":13.6247,"lng":-87.8936,"tz":"America/El_Salvador","p":13249},{"id":"3583905","n":"San Alejo","a":"San Alejo","lat":13.4314,"lng":-87.9631,"tz":"America/El_Salvador","p":5149},{"id":"3585480","n":"Intipucá","a":"Intipuca","lat":13.1969,"lng":-88.0544,"tz":"America/El_Salvador","p":3540},{"id":"3586917","n":"Conchagua","a":"Conchagua","lat":13.3078,"lng":-87.8647,"tz":"America/El_Salvador","p":3034},{"id":"3587372","n":"Anamorós","a":"Anamoros","lat":13.7406,"lng":-87.8736,"tz":"America/El_Salvador","p":2655},{"id":"3584264","n":"Nueva Esparta","a":"Nueva Esparta","lat":13.7836,"lng":-87.8386,"tz":"America/El_Salvador","p":2528},{"id":"3584140","n":"Pasaquina","a":"Pasaquina","lat":13.5844,"lng":-87.8411,"tz":"America/El_Salvador","p":2149}]},"03":{"name":"03","name_local":"03","cities":[{"id":"3587091","n":"Chalatenango","a":"Chalatenango","lat":14.0414,"lng":-88.9395,"tz":"America/El_Salvador","p":19364},{"id":"3584266","n":"Nueva Concepción","a":"Nueva Concepcion","lat":14.1333,"lng":-89.3,"tz":"America/El_Salvador","p":9990},{"id":"3583714","n":"San Francisco Morazán","a":"San Francisco Morazan","lat":14.1833,"lng":-89.05,"tz":"America/El_Salvador","p":506}]}}}